netbox_gitlab/__init__.py
netbox_gitlab/fields.py
netbox_gitlab/forms.py
netbox_gitlab/hacks.py
netbox_gitlab/models.py
netbox_gitlab/navigation.py
netbox_gitlab/signals.py
netbox_gitlab/template_content.py
netbox_gitlab/urls.py
netbox_gitlab/utils.py
netbox_gitlab/views.py
netbox_gitlab/migrations/0001_initial.py
netbox_gitlab/migrations/0002_traceelement.py
netbox_gitlab/migrations/__init__.py
netbox_gitlab/static/netbox_gitlab/style.css
netbox_gitlab/templates/netbox_gitlab/ask_branch.html
netbox_gitlab/templates/netbox_gitlab/diff_highlight_line.html
netbox_gitlab/templates/netbox_gitlab/error.html
netbox_gitlab/templates/netbox_gitlab/export_device.html
netbox_gitlab/templates/netbox_gitlab/export_interfaces.html
netbox_gitlab/templates/netbox_gitlab/export_inventory.html
netbox_gitlab/templates/netbox_gitlab/device/device_info.html
netbox_gitlab/templates/netbox_gitlab/device/update_interface_table.html
netbox_gitlab-0.6.1.dist-info/LICENSE.txt
netbox_gitlab-0.6.1.dist-info/METADATA
netbox_gitlab-0.6.1.dist-info/WHEEL
netbox_gitlab-0.6.1.dist-info/top_level.txt
netbox_gitlab-0.6.1.dist-info/RECORD
