Metadata-Version: 2.1
Name: netbox-gitlab
Version: 0.6.1
Summary: GitLab export to Ansible Inventory for NetBox
Home-page: https://github.com/solcon/netbox-gitlab
Author: Sander Steffann
Author-email: sander.steffann@isp.solcon.nl
License: Apache 2.0
Platform: UNKNOWN
Classifier: Development Status :: 3 - Alpha
Classifier: Framework :: Django
Classifier: Framework :: Django :: 3.0
Classifier: License :: OSI Approved :: Apache Software License
Classifier: Programming Language :: Python :: 3
Classifier: Programming Language :: Python :: 3.6
Classifier: Programming Language :: Python :: 3.7
Classifier: Programming Language :: Python :: 3.8
Requires-Python: >=3.6
Requires-Dist: setuptools
Requires-Dist: python-gitlab (==1.15.0)
